odoo/addons/product_supplierinfo_for_customer/README.rst
odoo/addons/product_supplierinfo_for_customer/__init__.py
odoo/addons/product_supplierinfo_for_customer/__manifest__.py
odoo/addons/product_supplierinfo_for_customer/demo/product_demo.xml
odoo/addons/product_supplierinfo_for_customer/i18n/ca.po
odoo/addons/product_supplierinfo_for_customer/i18n/de.po
odoo/addons/product_supplierinfo_for_customer/i18n/es.po
odoo/addons/product_supplierinfo_for_customer/i18n/fr.po
odoo/addons/product_supplierinfo_for_customer/i18n/it.po
odoo/addons/product_supplierinfo_for_customer/i18n/product_supplierinfo_for_customer.pot
odoo/addons/product_supplierinfo_for_customer/i18n/pt_BR.po
odoo/addons/product_supplierinfo_for_customer/i18n/sl.po
odoo/addons/product_supplierinfo_for_customer/models/__init__.py
odoo/addons/product_supplierinfo_for_customer/models/product_customerinfo.py
odoo/addons/product_supplierinfo_for_customer/models/product_pricelist.py
odoo/addons/product_supplierinfo_for_customer/models/product_product.py
odoo/addons/product_supplierinfo_for_customer/models/product_supplierinfo.py
odoo/addons/product_supplierinfo_for_customer/models/product_template.py
odoo/addons/product_supplierinfo_for_customer/models/res_partner.py
odoo/addons/product_supplierinfo_for_customer/readme/CONFIGURE.md
odoo/addons/product_supplierinfo_for_customer/readme/CONTRIBUTORS.md
odoo/addons/product_supplierinfo_for_customer/readme/DESCRIPTION.md
odoo/addons/product_supplierinfo_for_customer/readme/ROADMAP.md
odoo/addons/product_supplierinfo_for_customer/readme/USAGE.md
odoo/addons/product_supplierinfo_for_customer/security/ir.model.access.csv
odoo/addons/product_supplierinfo_for_customer/static/description/icon.png
odoo/addons/product_supplierinfo_for_customer/static/description/index.html
odoo/addons/product_supplierinfo_for_customer/static/xls/product_customerinfo.xls
odoo/addons/product_supplierinfo_for_customer/tests/__init__.py
odoo_addon_product_supplierinfo_for_customer-17.0.1.1.2.dist-info/METADATA
odoo_addon_product_supplierinfo_for_customer-17.0.1.1.2.dist-info/WHEEL
odoo_addon_product_supplierinfo_for_customer-17.0.1.1.2.dist-info/top_level.txt
odoo_addon_product_supplierinfo_for_customer-17.0.1.1.2.dist-info/RECORD
