Metadata-Version: 2.1
Name: odoo-addon-product_supplierinfo_for_customer
Version: 17.0.1.1.2
Requires-Python: >=3.10
Requires-Dist: odoo>=17.0a,<17.1dev
Summary: Allows to define prices for customers in the products
Home-page: https://github.com/OCA/product-attribute
License: AGPL-3
Author: AvanzOSC, Tecnativa, Odoo Community Association (OCA)
Author-email: support@odoo-community.org
Classifier: Programming Language :: Python
Classifier: Framework :: Odoo
Classifier: Framework :: Odoo :: 17.0
Classifier: License :: OSI Approved :: GNU Affero General Public License v3
Classifier: Development Status :: 5 - Production/Stable
